[
    {
    "id": 1001,
    "picture": "https://picsum.photos/id/237/250/150",
    "name": "andres",
    "lastname": "fernandez",
    "dni": 35500100,
    "address": "colon 2010",
    "cel": 2235988578,
    "city": "mar del plata",
    "mail": "andres_f89@hotmail.com",
    "comision": 10,
    "parkingName": "mdq parking"
    },
    {
        "id": 1002,
        "picture": "https://picsum.photos/id/237/250/150",
        "name": "jose",
        "lastname": "ledesma",
        "dni": 35500200,
        "address": "luro 2010",
        "cel": 2235988200,
        "city": "mar del plata",
        "mail": "jose@hotmail.com",
        "comision": 10,
        "parkingName": "mdq estacionamiento"
    },
    {
        "id": 1003,
        "picture": "https://picsum.photos/id/237/250/150",
        "name": "pedro",
        "lastname": "perez",
        "dni": 35500300,
        "address": "catamarca 2010",
        "cel": 2235988300,
        "city": "mar del plata",
        "mail": "pedro@hotmail.com",
        "comision": 10,
        "parkingName": "mdq garage"
    },
    {
        "id": 1004,
        "picture": "https://picsum.photos/id/237/250/150",
        "name": "micaela",
        "lastname": "garcia",
        "dni": 35500400,
        "address": "jujuy 2810",
        "cel": 2235988400,
        "city": "bariloche",
        "mail": "micaela@hotmail.com",
        "comision": 10,
        "parkingName": "bariloche parking"
    },
    {
        "id": 1005,
        "picture": "https://picsum.photos/id/237/250/150",
        "name": "rocio",
        "lastname": "iturrarte",
        "dni": 35500100,
        "address": "salta 500",
        "cel": 2235988500,
        "city": "salta",
        "mail": "rocio@hotmail.com",
        "comision": 10,
        "parkingName": "salta parking"
    },
    {
        "id": 1006,
        "picture": "https://picsum.photos/id/237/250/150",
        "name": "ramon",
        "lastname": "bauza",
        "dni": 35500600,
        "address": "colon 3456",
        "cel": 2235988600,
        "city": "cordoba",
        "mail": "ramon@hotmail.com",
        "comision": 10,
        "parkingName": "cordoba parking"
    }
]